README.md
setup.py
pymask/__init__.py
pymask/line_mask.py
pymask/poisson_mask.py
pymask/radial_mask.py
pymask/spiral_mask.py
pymask_gyl.egg-info/PKG-INFO
pymask_gyl.egg-info/SOURCES.txt
pymask_gyl.egg-info/dependency_links.txt
pymask_gyl.egg-info/requires.txt
pymask_gyl.egg-info/top_level.txt