Metadata-Version: 1.0
Name: pymask-gyl
Version: 0.0.6
Summary: tools for myself
Home-page: https://github.com
Author: charles
Author-email: endlesslights@163.com
License: UNKNOWN
Platform: UNKNOWN
